better_abc/__init__.py
better_abc/abc_meta.py
abc_property-1.0.dist-info/LICENSE
abc_property-1.0.dist-info/METADATA
abc_property-1.0.dist-info/WHEEL
abc_property-1.0.dist-info/top_level.txt
abc_property-1.0.dist-info/RECORD
