Metadata-Version: 2.1
Name: abc-property
Version: 1.0
Summary: Python ABC with a simple @abstract_property decorated checked after instantiation
Home-page: https://github.com/ndeutschmann/better_abc
Author: Nicolas Deutschmann
License: MIT
Platform: UNKNOWN
